{"name":"POST - As admin I have be able to assign a rating","id":"product;post---as-admin-i-have-be-able-to-assign-a-rating","testSteps":[{"number":1,"description":"Given I set POST api endpoint for assign rating","duration":161,"startTime":"2023-07-15T11:16:24.827055708+07:00[Asia/Jakarta]","result":"SUCCESS","precondition":false,"level":0,"children":[{"number":2,"description":"I set POST api endpoint for assign rating","duration":149,"startTime":"2023-07-15T11:16:24.836861006+07:00[Asia/Jakarta]","result":"SUCCESS","precondition":false,"level":1,"children":[{"number":3,"description":"GET https://altashop-api.fly.dev/api/products","duration":0,"startTime":"2023-07-15T11:16:24.983357675+07:00[Asia/Jakarta]","result":"SUCCESS","restQuery":{"method":"GET","path":"https://altashop-api.fly.dev/api/products","content":"","contentType":"application/json","requestHeaders":"Accept\u003d*/*\n\t\t\t\tContent-Type\u003dapplication/json","requestCookies":"","responseHeaders":"content-type: application/json\ndate: Sat, 15 Jul 2023 04:16:24 GMT\ntransfer-encoding: chunked\ncontent-encoding: gzip\nserver: Fly/a0b91024 (2023-06-13)\nvia: 1.1 fly.io\nfly-request-id: 01H5BW77BDCFTZ9DFM5GJN17FS-sin","responseCookies":"","responseBody":"{\n    \"data\": [\n        {\n            \"ID\": 85376,\n            \"Name\": \"Hp Vivo Y22\",\n            \"Description\": \"memiliki spesifikasi yang apik\",\n            \"Price\": 3000000,\n            \"Ratings\": 2,\n            \"Categories\": [\n                \n            ]\n        },\n        {\n            \"ID\": 85377,\n            \"Name\": \"Hp Vivo Y22\",\n            \"Description\": \"memiliki spesifikasi yang apik\",\n            \"Price\": 3000000,\n            \"Ratings\": 0,\n            \"Categories\": [\n                \n            ]\n        },\n        {\n            \"ID\": 85378,\n            \"Name\": \"Hp Vivo Y22\",\n            \"Description\": \"memiliki spesifikasi yang apik\",\n            \"Price\": 3000000,\n            \"Ratings\": 0,\n            \"Categories\": [\n                \n            ]\n        },\n        {\n            \"ID\": 85379,\n            \"Name\": \"Sony PS5\",\n            \"Description\": \"play has no limits\",\n            \"Price\": 299,\n            \"Ratings\": 0,\n            \"Categories\": [\n                \n            ]\n        },\n        {\n            \"ID\": 85380,\n            \"Name\": \"Sony PS5\",\n            \"Description\": \"play has no limits\",\n            \"Price\": 299,\n            \"Ratings\": 0,\n            \"Categories\": [\n                \n            ]\n        },\n        {\n            \"ID\": 85381,\n            \"Name\": \"Sony PS5\",\n            \"Description\": \"play has no limits\",\n            \"Price\": 299,\n            \"Ratings\": 0,\n            \"Categories\": [\n                \n            ]\n        },\n        {\n            \"ID\": 85382,\n            \"Name\": \"Sony PS5\",\n            \"Description\": \"play has no limits\",\n            \"Price\": 299,\n            \"Ratings\": 0,\n            \"Categories\": [\n                \n            ]\n        },\n        {\n            \"ID\": 85384,\n            \"Name\": \"IPHONE 15 PRO\",\n            \"Description\": \"HENGPON\",\n            \"Price\": 450,\n            \"Ratings\": 4,\n            \"Categories\": [\n                \n            ]\n        },\n        {\n            \"ID\": 85385,\n            \"Name\": \"Sony PS5\",\n            \"Description\": \"play has no limits\",\n            \"Price\": 299,\n            \"Ratings\": 0,\n            \"Categories\": [\n                \n            ]\n        },\n        {\n            \"ID\": 85386,\n            \"Name\": \"Sony PS5\",\n            \"Description\": \"play has no limits\",\n            \"Price\": 299,\n            \"Ratings\": 0,\n            \"Categories\": [\n                \n            ]\n        },\n        {\n            \"ID\": 85387,\n            \"Name\": \"Sony PS5 Slim\",\n            \"Description\": \"play has no limits\",\n            \"Price\": 299,\n            \"Ratings\": 0,\n            \"Categories\": [\n                \n            ]\n        },\n        {\n            \"ID\": 85388,\n            \"Name\": \"Sony PS5 Slim\",\n            \"Description\": \"play has no limits\",\n            \"Price\": 299,\n            \"Ratings\": 0,\n            \"Categories\": [\n                \n            ]\n        },\n        {\n            \"ID\": 85389,\n            \"Name\": \"Sony PS5 Slim\",\n            \"Description\": \"play has no limits\",\n            \"Price\": 299,\n            \"Ratings\": 0,\n            \"Categories\": [\n                \n            ]\n        },\n        {\n            \"ID\": 85390,\n            \"Name\": \"Sony PS5 Slim\",\n            \"Description\": \"play has no limits\",\n            \"Price\": 299,\n            \"Ratings\": 0,\n            \"Categories\": [\n                \n            ]\n        },\n        {\n            \"ID\": 85391,\n            \"Name\": \"Sony PS5 Slim\",\n            \"Description\": \"play has no limits\",\n            \"Price\": 299,\n            \"Ratings\": 0,\n            \"Categories\": [\n                \n            ]\n        },\n        {\n            \"ID\": 85392,\n            \"Name\": \"Sony PS5 Slim\",\n            \"Description\": \"play has no limits\",\n            \"Price\": 299,\n            \"Ratings\": 0,\n            \"Categories\": [\n                \n            ]\n        },\n        {\n            \"ID\": 85393,\n            \"Name\": \"Sony PS5 Slim\",\n            \"Description\": \"play has no limits\",\n            \"Price\": 299,\n            \"Ratings\": 0,\n            \"Categories\": [\n                \n            ]\n        },\n        {\n            \"ID\": 85394,\n            \"Name\": \"Sony PS5 Slim\",\n            \"Description\": \"play has no limits\",\n            \"Price\": 299,\n            \"Ratings\": 0,\n            \"Categories\": [\n                \n            ]\n        },\n        {\n            \"ID\": 85395,\n            \"Name\": \"Sony PS5 Slim\",\n            \"Description\": \"play has no limits\",\n            \"Price\": 299,\n            \"Ratings\": 0,\n            \"Categories\": [\n                \n            ]\n        },\n        {\n            \"ID\": 85396,\n            \"Name\": \"Sony PS5 Slim\",\n            \"Description\": \"play has no limits\",\n            \"Price\": 299,\n            \"Ratings\": 0,\n            \"Categories\": [\n                \n            ]\n        },\n        {\n            \"ID\": 85397,\n            \"Name\": \"Sony PS5 Slim\",\n            \"Description\": \"play has no limits\",\n            \"Price\": 299,\n            \"Ratings\": 0,\n            \"Categories\": [\n                \n            ]\n        }\n    ]\n}","statusCode":200},"precondition":false,"level":2}]}]},{"number":4,"description":"When I send POST request for assign rating","duration":492,"startTime":"2023-07-15T11:16:24.990371409+07:00[Asia/Jakarta]","result":"SUCCESS","precondition":false,"level":0,"children":[{"number":5,"description":"I send POST request for assign rating","duration":482,"startTime":"2023-07-15T11:16:24.993030554+07:00[Asia/Jakarta]","result":"SUCCESS","precondition":false,"level":1,"children":[{"number":6,"description":"POST https://altashop-api.fly.dev/api/auth/login","duration":0,"startTime":"2023-07-15T11:16:25.157434141+07:00[Asia/Jakarta]","result":"SUCCESS","restQuery":{"method":"POST","path":"https://altashop-api.fly.dev/api/auth/login","content":"{\n    \"password\": \"4hz77whm8\",\n    \"email\": \"zola.haag@example.com\"\n}","contentType":"application/json","requestHeaders":"Accept\u003d*/*\n\t\t\t\tContent-Type\u003dapplication/json","requestCookies":"","responseHeaders":"content-type: application/json\ndate: Sat, 15 Jul 2023 04:16:25 GMT\ncontent-encoding: gzip\ntransfer-encoding: chunked\nserver: Fly/a0b91024 (2023-06-13)\nvia: 1.1 fly.io\nfly-request-id: 01H5BW77HFZBCPRPWS8AFMXCR9-sin","responseCookies":"","responseBody":"{\n    \"data\": \"eyJhbGciOiJIUzI1NiIsInR5cCI6IkpXVCJ9.eyJGdWxsbmFtZSI6IkNsaW50IEdyaW1lcyIsIkVtYWlsIjoiem9sYS5oYWFnQGV4YW1wbGUuY29tIn0.qfIJSFYrSfTbx6iskjNip03TejXbFpip2TVdW9l1oL8\"\n}","statusCode":200},"precondition":false,"level":2},{"number":7,"description":"I set POST api endpoint for assign rating","duration":166,"startTime":"2023-07-15T11:16:25.160301201+07:00[Asia/Jakarta]","result":"SUCCESS","precondition":false,"level":2,"children":[{"number":8,"description":"GET https://altashop-api.fly.dev/api/products","duration":0,"startTime":"2023-07-15T11:16:25.325072508+07:00[Asia/Jakarta]","result":"SUCCESS","restQuery":{"method":"GET","path":"https://altashop-api.fly.dev/api/products","content":"","contentType":"application/json","requestHeaders":"Accept\u003d*/*\n\t\t\t\tContent-Type\u003dapplication/json","requestCookies":"","responseHeaders":"content-type: application/json\ndate: Sat, 15 Jul 2023 04:16:25 GMT\ntransfer-encoding: chunked\ncontent-encoding: gzip\nserver: Fly/a0b91024 (2023-06-13)\nvia: 1.1 fly.io\nfly-request-id: 01H5BW77NW09RA5ESMQTQX77B7-sin","responseCookies":"","responseBody":"{\n    \"data\": [\n        {\n            \"ID\": 85376,\n            \"Name\": \"Hp Vivo Y22\",\n            \"Description\": \"memiliki spesifikasi yang apik\",\n            \"Price\": 3000000,\n            \"Ratings\": 2,\n            \"Categories\": [\n                \n            ]\n        },\n        {\n            \"ID\": 85377,\n            \"Name\": \"Hp Vivo Y22\",\n            \"Description\": \"memiliki spesifikasi yang apik\",\n            \"Price\": 3000000,\n            \"Ratings\": 0,\n            \"Categories\": [\n                \n            ]\n        },\n        {\n            \"ID\": 85378,\n            \"Name\": \"Hp Vivo Y22\",\n            \"Description\": \"memiliki spesifikasi yang apik\",\n            \"Price\": 3000000,\n            \"Ratings\": 0,\n            \"Categories\": [\n                \n            ]\n        },\n        {\n            \"ID\": 85379,\n            \"Name\": \"Sony PS5\",\n            \"Description\": \"play has no limits\",\n            \"Price\": 299,\n            \"Ratings\": 0,\n            \"Categories\": [\n                \n            ]\n        },\n        {\n            \"ID\": 85380,\n            \"Name\": \"Sony PS5\",\n            \"Description\": \"play has no limits\",\n            \"Price\": 299,\n            \"Ratings\": 0,\n            \"Categories\": [\n                \n            ]\n        },\n        {\n            \"ID\": 85381,\n            \"Name\": \"Sony PS5\",\n            \"Description\": \"play has no limits\",\n            \"Price\": 299,\n            \"Ratings\": 0,\n            \"Categories\": [\n                \n            ]\n        },\n        {\n            \"ID\": 85382,\n            \"Name\": \"Sony PS5\",\n            \"Description\": \"play has no limits\",\n            \"Price\": 299,\n            \"Ratings\": 0,\n            \"Categories\": [\n                \n            ]\n        },\n        {\n            \"ID\": 85384,\n            \"Name\": \"IPHONE 15 PRO\",\n            \"Description\": \"HENGPON\",\n            \"Price\": 450,\n            \"Ratings\": 4,\n            \"Categories\": [\n                \n            ]\n        },\n        {\n            \"ID\": 85385,\n            \"Name\": \"Sony PS5\",\n            \"Description\": \"play has no limits\",\n            \"Price\": 299,\n            \"Ratings\": 0,\n            \"Categories\": [\n                \n            ]\n        },\n        {\n            \"ID\": 85386,\n            \"Name\": \"Sony PS5\",\n            \"Description\": \"play has no limits\",\n            \"Price\": 299,\n            \"Ratings\": 0,\n            \"Categories\": [\n                \n            ]\n        },\n        {\n            \"ID\": 85387,\n            \"Name\": \"Sony PS5 Slim\",\n            \"Description\": \"play has no limits\",\n            \"Price\": 299,\n            \"Ratings\": 0,\n            \"Categories\": [\n                \n            ]\n        },\n        {\n            \"ID\": 85388,\n            \"Name\": \"Sony PS5 Slim\",\n            \"Description\": \"play has no limits\",\n            \"Price\": 299,\n            \"Ratings\": 0,\n            \"Categories\": [\n                \n            ]\n        },\n        {\n            \"ID\": 85389,\n            \"Name\": \"Sony PS5 Slim\",\n            \"Description\": \"play has no limits\",\n            \"Price\": 299,\n            \"Ratings\": 0,\n            \"Categories\": [\n                \n            ]\n        },\n        {\n            \"ID\": 85390,\n            \"Name\": \"Sony PS5 Slim\",\n            \"Description\": \"play has no limits\",\n            \"Price\": 299,\n            \"Ratings\": 0,\n            \"Categories\": [\n                \n            ]\n        },\n        {\n            \"ID\": 85391,\n            \"Name\": \"Sony PS5 Slim\",\n            \"Description\": \"play has no limits\",\n            \"Price\": 299,\n            \"Ratings\": 0,\n            \"Categories\": [\n                \n            ]\n        },\n        {\n            \"ID\": 85392,\n            \"Name\": \"Sony PS5 Slim\",\n            \"Description\": \"play has no limits\",\n            \"Price\": 299,\n            \"Ratings\": 0,\n            \"Categories\": [\n                \n            ]\n        },\n        {\n            \"ID\": 85393,\n            \"Name\": \"Sony PS5 Slim\",\n            \"Description\": \"play has no limits\",\n            \"Price\": 299,\n            \"Ratings\": 0,\n            \"Categories\": [\n                \n            ]\n        },\n        {\n            \"ID\": 85394,\n            \"Name\": \"Sony PS5 Slim\",\n            \"Description\": \"play has no limits\",\n            \"Price\": 299,\n            \"Ratings\": 0,\n            \"Categories\": [\n                \n            ]\n        },\n        {\n            \"ID\": 85395,\n            \"Name\": \"Sony PS5 Slim\",\n            \"Description\": \"play has no limits\",\n            \"Price\": 299,\n            \"Ratings\": 0,\n            \"Categories\": [\n                \n            ]\n        },\n        {\n            \"ID\": 85396,\n            \"Name\": \"Sony PS5 Slim\",\n            \"Description\": \"play has no limits\",\n            \"Price\": 299,\n            \"Ratings\": 0,\n            \"Categories\": [\n                \n            ]\n        },\n        {\n            \"ID\": 85397,\n            \"Name\": \"Sony PS5 Slim\",\n            \"Description\": \"play has no limits\",\n            \"Price\": 299,\n            \"Ratings\": 0,\n            \"Categories\": [\n                \n            ]\n        }\n    ]\n}","statusCode":200},"precondition":false,"level":3}]},{"number":9,"description":"POST https://altashop-api.fly.dev/api/products/85376/ratings","duration":0,"startTime":"2023-07-15T11:16:25.475346677+07:00[Asia/Jakarta]","result":"SUCCESS","restQuery":{"method":"POST","path":"https://altashop-api.fly.dev/api/products/85376/ratings","content":"{\n    \"count\": 4\n}","contentType":"application/json","requestHeaders":"Authorization\u003dBearer eyJhbGciOiJIUzI1NiIsInR5cCI6IkpXVCJ9.eyJGdWxsbmFtZSI6IkNsaW50IEdyaW1lcyIsIkVtYWlsIjoiem9sYS5oYWFnQGV4YW1wbGUuY29tIn0.qfIJSFYrSfTbx6iskjNip03TejXbFpip2TVdW9l1oL8\n\t\t\t\tAccept\u003d*/*\n\t\t\t\tContent-Type\u003dapplication/json","requestCookies":"","responseHeaders":"content-type: application/json\ndate: Sat, 15 Jul 2023 04:16:25 GMT\ncontent-encoding: gzip\ntransfer-encoding: chunked\nserver: Fly/a0b91024 (2023-06-13)\nvia: 1.1 fly.io\nfly-request-id: 01H5BW77V6WVB73X0MQ8FCSD1W-sin","responseCookies":"","responseBody":"{\n    \"data\": {\n        \"ID\": 85376,\n        \"Name\": \"Hp Vivo Y22\",\n        \"Description\": \"memiliki spesifikasi yang apik\",\n        \"Price\": 3000000,\n        \"Ratings\": 2,\n        \"Categories\": [\n            \n        ]\n    }\n}","statusCode":200},"precondition":false,"level":2}]}]},{"number":10,"description":"Then I receive valid HTTP response code 200","duration":6,"startTime":"2023-07-15T11:16:25.486143384+07:00[Asia/Jakarta]","result":"SUCCESS","precondition":false,"level":0,"children":[{"number":11,"description":"I receive valid HTTP response code 200","duration":2,"startTime":"2023-07-15T11:16:25.488091284+07:00[Asia/Jakarta]","result":"SUCCESS","precondition":false,"level":1}]}],"userStory":{"id":"product","storyName":"Product","displayName":"Product","path":"file:///home/nadir/IdeaProjects/minproQE/src/test/resources/api/Product.feature","narrative":"  As a admin\n  I want to see list of product\n  So that I can create new product","type":"feature","qualifiedTag":{"name":"Api/Product","type":"feature","displayName":"Api/Product"}},"featureTag":{"name":"Api/Product","type":"feature","displayName":"Api/Product"},"title":"POST - As admin I have be able to assign a rating","description":"","allTags":[{"name":"Api/Product","type":"feature","displayName":"Api/Product"}],"startTime":"2023-07-15T11:16:24.823004954+07:00[Asia/Jakarta]","duration":671,"projectKey":"","isManualTestingUpToDate":false,"context":"linux","manual":false,"testSource":"Cucumber","result":"SUCCESS"}